{"Pick data file": "proxy_pick_data.csv", "Result": {"successful": 1, "unsuccessful": 0, "column": "last"}, "Data channels": [{"name": "Wrist force", "index_offset": 0, "dimensions": 3, "units": "N", "stats": [{"Min": -11.99637522, "Max": 8.516101548, "Mean": -0.808979083770909, "SD": 2.1235892757942985}, {"Min": -7.359372998, "Max": 14.17138982, "Mean": 2.6408346482928406, "SD": 2.8792584463149726}, {"Min": -15.00038534, "Max": 20.03698308, "Mean": -2.970809780405455, "SD": 4.426815649945686}]}, {"name": "Wrist torque", "index_offset": 3, "dimensions": 3, "units": "N.m", "stats": [{"Min": -1.099683908, "Max": 1.070451089, "Mean": -0.22816099250064392, "SD": 0.20878583773851728}, {"Min": -1.24642742, "Max": 0.607428456, "Mean": -0.08235645442053031, "SD": 0.1825844421076967}, {"Min": -0.62552044, "Max": 0.340460618, "Mean": 0.01800652827314394, "SD": 0.12296693121622884}]}, {"name": "IMU accel f1", "index_offset": 6, "dimensions": 3, "units": "gravity units", "stats": [{"Min": -19.61330032, "Max": 19.61270142, "Mean": -1.3160617767691667, "SD": 2.9390712606442895}, {"Min": -19.61330032, "Max": 19.61270142, "Mean": -6.869213043341439, "SD": 4.255234440477789}, {"Min": -19.61330032, "Max": 19.61270142, "Mean": -3.0957111987847727, "SD": 4.854995831248282}]}, {"name": "IMU accel f2", "index_offset": 15, "dimensions": 3, "units": "gravity units", "stats": [{"Min": -19.61330032, "Max": 19.61270142, "Mean": -2.700274933616477, "SD": 2.894681909215833}, {"Min": -19.61330032, "Max": 19.61270142, "Mean": -4.789253953552008, "SD": 3.4333366287322296}, {"Min": -19.61330032, "Max": 19.61270142, "Mean": 5.3220345052616285, "SD": 4.781526385398198}]}, {"name": "IMU accel f3", "index_offset": 24, "dimensions": 3, "units": "gravity units", "stats": [{"Min": -19.61330032, "Max": 19.61270142, "Mean": -1.332792239995985, "SD": 2.949917639363758}, {"Min": -19.61330032, "Max": 19.61270142, "Mean": -6.840580232965492, "SD": 4.28889756568898}, {"Min": -19.61330032, "Max": 19.61270142, "Mean": -3.118416990204697, "SD": 4.886564958354453}]}, {"name": "IMU velocity f1", "index_offset": 9, "dimensions": 3, "units": "deg/sec", "stats": [{"Min": -250.0, "Max": 249.9923706, "Mean": 19.46334020052534, "SD": 65.44141968036514}, {"Min": -250.0, "Max": 249.9923706, "Mean": -1.1851070384760227, "SD": 12.91258915506432}, {"Min": -250.0, "Max": 203.5522461, "Mean": -1.639763899525076, "SD": 13.9601042365717}]}, {"name": "IMU velocity f2", "index_offset": 18, "dimensions": 3, "units": "deg/sec", "stats": [{"Min": -250.0, "Max": 249.9923706, "Mean": 17.38780850104246, "SD": 56.13704309511917}, {"Min": -250.0, "Max": 249.9923706, "Mean": -0.5001927867142045, "SD": 15.283898561340763}, {"Min": -226.6921997, "Max": 197.7767944, "Mean": -3.023863946557689, "SD": 14.565549629977495}]}, {"name": "IMU velocity f3", "index_offset": 27, "dimensions": 3, "units": "deg/sec", "stats": [{"Min": -209.9151611, "Max": 249.9923706, "Mean": 19.962433034581515, "SD": 65.90506003011951}, {"Min": -250.0, "Max": 249.9923706, "Mean": -0.9358566457620454, "SD": 12.279990485438196}, {"Min": -192.3294067, "Max": 211.8301392, "Mean": -1.8142208908503787, "SD": 13.849002795195796}]}, {"name": "Motor position f1", "index_offset": 12, "dimensions": 1, "units": "radians", "stats": [{"Min": 179.9599915, "Max": 430.1440125, "Mean": 368.06999205969703, "SD": 71.07686771291644}]}, {"name": "Motor position f2", "index_offset": 21, "dimensions": 1, "units": "radians", "stats": [{"Min": 140.0079956, "Max": 260.3039856, "Mean": 232.08732027486366, "SD": 47.50755544854799}]}, {"name": "Motor position f3", "index_offset": 30, "dimensions": 1, "units": "radians", "stats": [{"Min": 93.98400116, "Max": 220.0, "Mean": 186.4358564585591, "SD": 46.047608687487134}]}, {"name": "Motor velocity f1", "index_offset": 13, "dimensions": 1, "units": "rad/sec", "stats": [{"Min": 0.0, "Max": 266.5559998, "Mean": 37.167846440975424, "SD": 89.15549577577617}]}, {"name": "Motor velocity f2", "index_offset": 22, "dimensions": 1, "units": "rad/sec", "stats": [{"Min": 0.0, "Max": 272.052002, "Mean": 32.82761807730337, "SD": 85.30877971918527}]}, {"name": "Motor velocity f3", "index_offset": 31, "dimensions": 1, "units": "rad/sec", "stats": [{"Min": 0.0, "Max": 270.6779785, "Mean": 32.180372767104124, "SD": 83.88365935249561}]}, {"name": "Motor effort f1", "index_offset": 14, "dimensions": 1, "units": "amp", "stats": [{"Min": -330.8699951, "Max": 174.8500061, "Mean": 35.32253659580265, "SD": 33.617106097552536}]}, {"name": "Motor effort f2", "index_offset": 23, "dimensions": 1, "units": "amp", "stats": [{"Min": -287.8300171, "Max": 285.1400146, "Mean": 37.98398913211852, "SD": 38.369459557919974}]}, {"name": "Motor effort f3", "index_offset": 32, "dimensions": 1, "units": "amp", "stats": [{"Min": -312.0400085, "Max": 330.8699951, "Mean": 53.83586756616258, "SD": 49.550967697282864}]}], "n_total_dims": 33, "n_time_steps": 40, "By name": {"Wrist force": 0, "Wrist torque": 1, "IMU accel f1": 2, "IMU accel f2": 3, "IMU accel f3": 4, "IMU velocity f1": 5, "IMU velocity f2": 6, "IMU velocity f3": 7, "Motor position f1": 8, "Motor position f2": 9, "Motor position f3": 10, "Motor velocity f1": 11, "Motor velocity f2": 12, "Motor velocity f3": 13, "Motor effort f1": 14, "Motor effort f2": 15, "Motor effort f3": 16}}